{
    "dev1": {"min": 90, "max": 100, "voltage": 230},
    "dev2": {"min": 1100, "max": 1200, "voltage": 230},
    "dev3": {"min": 600, "max": 620, "voltage": 230},
    "dev4": {"min": 1800, "max": 1900, "voltage": 230},
    "dev5": {"min": 50, "max": 100, "voltage": 230},
    "dev6": {"min": 2000, "max": 2100, "voltage": 230},
    "dev7": {"min": 1500, "max": 1600, "voltage": 230},
    "dev8": {"min": 0, "max": 1, "voltage": 230},
    "dev9": {"min": 150, "max": 200, "voltage": 230},
    "dev10": {"min": 0, "max": 1, "voltage": 230},
    "dev11": {"min": 1400, "max": 1499, "voltage": 230}
}